pyjags_arviz/__init__.py
pyjags_arviz-0.0.3.dist-info/LICENSE
pyjags_arviz-0.0.3.dist-info/METADATA
pyjags_arviz-0.0.3.dist-info/WHEEL
pyjags_arviz-0.0.3.dist-info/top_level.txt
pyjags_arviz-0.0.3.dist-info/RECORD
