Metadata-Version: 2.1
Name: pyjags-arviz
Version: 0.0.3
Summary: Makes MCMC samples from PyJAGS usable in ArviZ
Home-page: https://github.com/michaelnowotny/pyjags_arviz
Author: Michael Christoph Nowotny
Author-email: nowotnym@gmail.com
License: MIT
Platform: UNKNOWN
Classifier: License :: OSI Approved :: MIT License
Classifier: Programming Language :: Python
Classifier: Programming Language :: Python :: 3
Classifier: Programming Language :: Python :: 3.6
Classifier: Programming Language :: Python :: 3.7
Classifier: Programming Language :: Python :: Implementation :: CPython
Requires-Python: >=3.6.0
Requires-Dist: arviz
Requires-Dist: numpy
